check_covid/__init__.py
Check_Covid-1.0.0.dist-info/METADATA
Check_Covid-1.0.0.dist-info/WHEEL
Check_Covid-1.0.0.dist-info/top_level.txt
Check_Covid-1.0.0.dist-info/RECORD
