Metadata-Version: 2.1
Name: Check-Covid
Version: 1.0.0
Summary: Check Covid: Check Covid Tests without all the fuzz
Home-page: https://github.com/TvoozMagnificent/
Author: Number Basher
Author-email: luchang1106@icloud.com
License: MIT
Classifier: License :: OSI Approved :: MIT License
Classifier: Programming Language :: Python :: 3
Classifier: Programming Language :: Python :: 3.11
Requires-Dist: pyautogui
Requires-Dist: pyperclip
